README.txt
setup.py
pyf/__init__.py
pyf.dataflow.egg-info/PKG-INFO
pyf.dataflow.egg-info/SOURCES.txt
pyf.dataflow.egg-info/dependency_links.txt
pyf.dataflow.egg-info/entry_points.txt
pyf.dataflow.egg-info/namespace_packages.txt
pyf.dataflow.egg-info/not-zip-safe
pyf.dataflow.egg-info/requires.txt
pyf.dataflow.egg-info/top_level.txt
pyf/dataflow/__init__.py
pyf/dataflow/components.py
pyf/dataflow/core.py
pyf/dataflow/merging.py
pyf/dataflow/reordering.py