Metadata-Version: 1.0
Name: pyf.dataflow
Version: 2.0.2
Summary: Core DataFlow system of PyF framework
Home-page: http://pyfproject.org
Author: UNKNOWN
Author-email: UNKNOWN
License: LGPL
Platform: UNKNOWN
Classifier: Programming Language :: Python
Classifier: Development Status :: 4 - Beta
